lahap/__init__.py
lahap/lahap.py
lahap/services/__init__.py
lahap/services/athena.py
lahap/services/glue.py
lahap/services/s3.py
Lahap-0.2.1.dist-info/LICENSE
Lahap-0.2.1.dist-info/METADATA
Lahap-0.2.1.dist-info/WHEEL
Lahap-0.2.1.dist-info/top_level.txt
Lahap-0.2.1.dist-info/RECORD
