Metadata-Version: 2.1
Name: Lahap
Version: 0.2.1
Summary: Utility package to AWS Athena and AWS Glue.
Home-page: https://github.com/erathoslabs/lahap
Author: Erathos
Author-email: heron@erathos.com
License: MIT
Platform: UNKNOWN
Requires-Dist: boto3
